pyhut/config.py
pyhut/server.py
pyhut-0.1.3.dist-info/LICENSE
pyhut-0.1.3.dist-info/METADATA
pyhut-0.1.3.dist-info/WHEEL
pyhut-0.1.3.dist-info/top_level.txt
pyhut-0.1.3.dist-info/RECORD
