Metadata-Version: 2.1
Name: pyhut
Version: 0.1.3
Summary: Package for Minehut Minecraft server API
Home-page: https://github.com/thunder4lpha/pyhut
Author: thunder4lpha
License: UNKNOWN
Platform: UNKNOWN
Classifier: Programming Language :: Python :: 3
Classifier: License :: OSI Approved :: MIT License
Classifier: Operating System :: OS Independent
Requires-Python: >=3.6
